CMakeLists.txt
LICENSE
MANIFEST.in
README.md
setup.py
cmake/FindLTO.cmake
cmake/FindPython.cmake
cmake/FindSvar.cmake.in
cmake/FindSystem.cmake
cmake/PICMake.cmake
cmake/tab_completion.cmake
cmake/tab_completion.sh
doc/Doxyfile
doc/how-to-packaging-pypi.md
doc/doxygen/1_compile.dox
doc/doxygen/2_json.dox
doc/doxygen/3_argument.dox
doc/doxygen/4_dynamic.dox
doc/doxygen/5_module.dox
doc/doxygen/6_languages.dox
doc/doxygen/main.dox
doc/images/svar_vs_pybind11.png
src/README.md
src/Svar/Svar.h
src/java/SvarAndroid/.gitignore
src/java/SvarAndroid/build.gradle
src/java/SvarAndroid/gradle.properties
src/java/SvarAndroid/gradlew
src/java/SvarAndroid/gradlew.bat
src/java/SvarAndroid/settings.gradle
src/java/SvarAndroid/app/.gitignore
src/java/SvarAndroid/app/CMakeLists.txt
src/java/SvarAndroid/app/build.gradle
src/java/SvarAndroid/app/proguard-rules.pro
src/java/SvarAndroid/app/src/androidTest/java/com/rtmapper/myapplication/ExampleInstrumentedTest.java
src/java/SvarAndroid/app/src/main/AndroidManifest.xml
src/java/SvarAndroid/app/src/main/cpp/Svar.h
src/java/SvarAndroid/app/src/main/cpp/native-lib.cpp
src/java/SvarAndroid/app/src/main/java/com/rtmapper/myapplication/MainActivity.java
src/java/SvarAndroid/app/src/main/res/layout/activity_main.xml
src/java/SvarAndroid/app/src/main/res/layout/content_main.xml
src/java/SvarAndroid/app/src/main/res/menu/menu_main.xml
src/java/SvarAndroid/app/src/main/res/mipmap-hdpi/ic_launcher.png
src/java/SvarAndroid/app/src/main/res/mipmap-hdpi/ic_launcher_round.png
src/java/SvarAndroid/app/src/main/res/mipmap-mdpi/ic_launcher.png
src/java/SvarAndroid/app/src/main/res/mipmap-mdpi/ic_launcher_round.png
src/java/SvarAndroid/app/src/main/res/mipmap-xhdpi/ic_launcher.png
src/java/SvarAndroid/app/src/main/res/mipmap-xhdpi/ic_launcher_round.png
src/java/SvarAndroid/app/src/main/res/mipmap-xxhdpi/ic_launcher.png
src/java/SvarAndroid/app/src/main/res/mipmap-xxhdpi/ic_launcher_round.png
svar.egg-info/PKG-INFO
svar.egg-info/SOURCES.txt
svar.egg-info/dependency_links.txt
svar.egg-info/not-zip-safe
svar.egg-info/top_level.txt